python_workflow_definition/__init__.py
python_workflow_definition/aiida.py
python_workflow_definition/executorlib.py
python_workflow_definition/jobflow.py
python_workflow_definition/models.py
python_workflow_definition/plot.py
python_workflow_definition/purepython.py
python_workflow_definition/pyiron_base.py
python_workflow_definition/pyiron_workflow.py
python_workflow_definition/shared.py
python_workflow_definition/cwl/__init__.py
python_workflow_definition/cwl/__main__.py
python_workflow_definition-0.1.2.dist-info/METADATA
python_workflow_definition-0.1.2.dist-info/WHEEL
python_workflow_definition-0.1.2.dist-info/licenses/LICENSE
python_workflow_definition-0.1.2.dist-info/RECORD
