Metadata-Version: 2.4
Name: python_workflow_definition
Version: 0.1.2
Summary: Python Workflow Definition - workflow interoperability for aiida, jobflow and pyiron
Author-email: Jan Janssen <janssen@mpie.de>, Janine George <janine.geogre@bam.de>, Julian Geiger <julian.geiger@psi.ch>, Xing Wang <xing.wang@psi.ch>, Marnik Bercx <marnik.bercx@psi.ch>, Christina Ertural <christina.ertural@bam.de>
License: BSD 3-Clause License
License-File: LICENSE
Requires-Dist: numpy>=1.21
Requires-Dist: pydantic<=2.12.4,>=2.7.0
Provides-Extra: aiida
Requires-Dist: aiida-workgraph<=0.7.6,>=0.5.1; extra == 'aiida'
Provides-Extra: jobflow
Requires-Dist: jobflow<=0.2.1,>=0.1.18; extra == 'jobflow'
Provides-Extra: plot
Requires-Dist: ipython<=9.8.0,>=7.33.0; extra == 'plot'
Requires-Dist: networkx<=3.5,>=2.8.8; extra == 'plot'
Requires-Dist: pygraphviz<=1.14,>=1.10; extra == 'plot'
Provides-Extra: pyiron
Requires-Dist: pyiron-base<=0.15.10,>=0.11.10; extra == 'pyiron'
